timestamps/__init__.py
timestamps/apps.py
timestamps/managers.py
timestamps/models.py
timestamps/querysets.py
timestamps/drf/__init__.py
timestamps/drf/mixins.py
timestamps/drf/permissions.py
timestamps/drf/routers.py
timestamps/drf/utils.py
timestamps/drf/viewsets.py
django_timestampable-1.0.4.dist-info/LICENSE
django_timestampable-1.0.4.dist-info/METADATA
django_timestampable-1.0.4.dist-info/WHEEL
django_timestampable-1.0.4.dist-info/top_level.txt
django_timestampable-1.0.4.dist-info/RECORD
