Metadata-Version: 2.1
Name: django-timestampable
Version: 1.0.4
Summary: Timestamps and Soft Delete Patterns in Django Models
Home-page: https://github.com/xgeekshq/django-timestampable/
Author: Daniel Pinto
Author-email: dmp593@gmail.com
License: MIT
Classifier: Environment :: Web Environment
Classifier: Framework :: Django
Classifier: Framework :: Django :: 3.1
Classifier: Framework :: Django :: 3.2
Classifier: Framework :: Django :: 4.0
Classifier: Intended Audience :: Developers
Classifier: License :: OSI Approved :: MIT License
Classifier: Operating System :: OS Independent
Classifier: Programming Language :: Python
Classifier: Programming Language :: Python :: 3
Classifier: Programming Language :: Python :: 3 :: Only
Classifier: Programming Language :: Python :: 3.6
Classifier: Programming Language :: Python :: 3.7
Classifier: Programming Language :: Python :: 3.8
Classifier: Programming Language :: Python :: 3.9
Classifier: Programming Language :: Python :: 3.10
Classifier: Topic :: Software Development :: Libraries
Classifier: Topic :: Software Development :: Libraries :: Application Frameworks
Requires-Python: >=3.6
License-File: LICENSE
Requires-Dist: Django (>=3.1)
Requires-Dist: aspectlib (>=1.5)
Provides-Extra: drf
Requires-Dist: djangorestframework (>=3.12) ; extra == 'drf'
